[
  {
    "model": "commons.skill",
    "fields": {
      "name": ".NET Core",
      "skill_type": "T",
      "created_on": "2022-07-01T09:00:00.000Z"
    }
  },
  {
    "model": "commons.skill",
    "fields": {
      "name": "ADO.NET",
      "skill_type": "T",
      "created_on": "2022-07-01T09:00:00.000Z"
    }
  },
  {
    "model": "commons.skill",
    "fields": {
      "name": "ASP.NET",
      "skill_type": "T",
      "created_on": "2022-07-01T09:00:00.000Z"
    }
  },
  {
    "model": "commons.skill",
    "fields": {
      "name": "ASP.NET MVC",
      "skill_type": "T",
      "created_on": "2022-07-01T09:00:00.000Z"
    }
  },
  {
    "model": "commons.skill",
    "fields": {
      "name": "ASP.NET Web API",
      "skill_type": "T",
      "created_on": "2022-07-01T09:00:00.000Z"
    }
  },
  {
    "model": "commons.skill",
    "fields": {
      "name": "Agile & Scrum",
      "skill_type": "T",
      "created_on": "2022-07-01T09:00:00.000Z"
    }
  },
  {
    "model": "commons.skill",
    "fields": {
      "name": "Android",
      "skill_type": "T",
      "created_on": "2022-07-01T09:00:00.000Z"
    }
  },
  {
    "model": "commons.skill",
    "fields": {
      "name": "Angular",
      "skill_type": "T",
      "created_on": "2022-07-01T09:00:00.000Z"
    }
  },
  {
    "model": "commons.skill",
    "fields": {
      "name": "AngularJS",
      "skill_type": "T",
      "created_on": "2022-07-01T09:00:00.000Z"
    }
  },
  {
    "model": "commons.skill",
    "fields": {
      "name": "Azure",
      "skill_type": "T",
      "created_on": "2022-07-01T09:00:00.000Z"
    }
  },
  {
    "model": "commons.skill",
    "fields": {
      "name": "C#",
      "skill_type": "T",
      "created_on": "2022-07-01T09:00:00.000Z"
    }
  },
  {
    "model": "commons.skill",
    "fields": {
      "name": "CSS",
      "skill_type": "T",
      "created_on": "2022-07-01T09:00:00.000Z"
    }
  },
  {
    "model": "commons.skill",
    "fields": {
      "name": "Dependency Injection",
      "skill_type": "T",
      "created_on": "2022-07-01T09:00:00.000Z"
    }
  },
  {
    "model": "commons.skill",
    "fields": {
      "name": "Design Patterns",
      "skill_type": "T",
      "created_on": "2022-07-01T09:00:00.000Z"
    }
  },
  {
    "model": "commons.skill",
    "fields": {
      "name": "DevOps",
      "skill_type": "T",
      "created_on": "2022-07-01T09:00:00.000Z"
    }
  },
  {
    "model": "commons.skill",
    "fields": {
      "name": "Entity Framework",
      "skill_type": "T",
      "created_on": "2022-07-01T09:00:00.000Z"
    }
  },
  {
    "model": "commons.skill",
    "fields": {
      "name": "Flutter",
      "skill_type": "T",
      "created_on": "2022-07-01T09:00:00.000Z"
    }
  },
  {
    "model": "commons.skill",
    "fields": {
      "name": "Git",
      "skill_type": "T",
      "created_on": "2022-07-01T09:00:00.000Z"
    }
  },
  {
    "model": "commons.skill",
    "fields": {
      "name": "Golang",
      "skill_type": "T",
      "created_on": "2022-07-01T09:00:00.000Z"
    }
  },
  {
    "model": "commons.skill",
    "fields": {
      "name": "GraphQL",
      "skill_type": "T",
      "created_on": "2022-07-01T09:00:00.000Z"
    }
  },
  {
    "model": "commons.skill",
    "fields": {
      "name": "HTML5",
      "skill_type": "T",
      "created_on": "2022-07-01T09:00:00.000Z"
    }
  },
  {
    "model": "commons.skill",
    "fields": {
      "name": "Ionic",
      "skill_type": "T",
      "created_on": "2022-07-01T09:00:00.000Z"
    }
  },
  {
    "model": "commons.skill",
    "fields": {
      "name": "Java",
      "skill_type": "T",
      "created_on": "2022-07-01T09:00:00.000Z"
    }
  },
  {
    "model": "commons.skill",
    "fields": {
      "name": "JavaScript",
      "skill_type": "T",
      "created_on": "2022-07-01T09:00:00.000Z"
    }
  },
  {
    "model": "commons.skill",
    "fields": {
      "name": "Kotlin",
      "skill_type": "T",
      "created_on": "2022-07-01T09:00:00.000Z"
    }
  },
  {
    "model": "commons.skill",
    "fields": {
      "name": "LINQ",
      "skill_type": "T",
      "created_on": "2022-07-01T09:00:00.000Z"
    }
  },
  {
    "model": "commons.skill",
    "fields": {
      "name": "Laravel",
      "skill_type": "T",
      "created_on": "2022-07-01T09:00:00.000Z"
    }
  },
  {
    "model": "commons.skill",
    "fields": {
      "name": "MongoDB",
      "skill_type": "T",
      "created_on": "2022-07-01T09:00:00.000Z"
    }
  },
  {
    "model": "commons.skill",
    "fields": {
      "name": "MySQL",
      "skill_type": "T",
      "created_on": "2022-07-01T09:00:00.000Z"
    }
  },
  {
    "model": "commons.skill",
    "fields": {
      "name": "Node.js",
      "skill_type": "T",
      "created_on": "2022-07-01T09:00:00.000Z"
    }
  },
  {
    "model": "commons.skill",
    "fields": {
      "name": "OOP",
      "skill_type": "T",
      "created_on": "2022-07-01T09:00:00.000Z"
    }
  },
  {
    "model": "commons.skill",
    "fields": {
      "name": "Objective-C",
      "skill_type": "T",
      "created_on": "2022-07-01T09:00:00.000Z"
    }
  },
  {
    "model": "commons.skill",
    "fields": {
      "name": "PHP",
      "skill_type": "T",
      "created_on": "2022-07-01T09:00:00.000Z"
    }
  },
  {
    "model": "commons.skill",
    "fields": {
      "name": "PWA",
      "skill_type": "T",
      "created_on": "2022-07-01T09:00:00.000Z"
    }
  },
  {
    "model": "commons.skill",
    "fields": {
      "name": "Python",
      "skill_type": "T",
      "created_on": "2022-07-01T09:00:00.000Z"
    }
  },
  {
    "model": "commons.skill",
    "fields": {
      "name": "React",
      "skill_type": "T",
      "created_on": "2022-07-01T09:00:00.000Z"
    }
  },
  {
    "model": "commons.skill",
    "fields": {
      "name": "React Hooks",
      "skill_type": "T",
      "created_on": "2022-07-01T09:00:00.000Z"
    }
  },
  {
    "model": "commons.skill",
    "fields": {
      "name": "React Native",
      "skill_type": "T",
      "created_on": "2022-07-01T09:00:00.000Z"
    }
  },
  {
    "model": "commons.skill",
    "fields": {
      "name": "Reactive Programming",
      "skill_type": "T",
      "created_on": "2022-07-01T09:00:00.000Z"
    }
  },
  {
    "model": "commons.skill",
    "fields": {
      "name": "Redis",
      "skill_type": "T",
      "created_on": "2022-07-01T09:00:00.000Z"
    }
  },
  {
    "model": "commons.skill",
    "fields": {
      "name": "Redux",
      "skill_type": "T",
      "created_on": "2022-07-01T09:00:00.000Z"
    }
  },
  {
    "model": "commons.skill",
    "fields": {
      "name": "Ruby",
      "skill_type": "T",
      "created_on": "2022-07-01T09:00:00.000Z"
    }
  },
  {
    "model": "commons.skill",
    "fields": {
      "name": "Ruby on Rails",
      "skill_type": "T",
      "created_on": "2022-07-01T09:00:00.000Z"
    }
  },
  {
    "model": "commons.skill",
    "fields": {
      "name": "SQL",
      "skill_type": "T",
      "created_on": "2022-07-01T09:00:00.000Z"
    }
  },
  {
    "model": "commons.skill",
    "fields": {
      "name": "Spring",
      "skill_type": "T",
      "created_on": "2022-07-01T09:00:00.000Z"
    }
  },
  {
    "model": "commons.skill",
    "fields": {
      "name": "T-SQL",
      "skill_type": "T",
      "created_on": "2022-07-01T09:00:00.000Z"
    }
  },
  {
    "model": "commons.skill",
    "fields": {
      "name": "TypeScript",
      "skill_type": "T",
      "created_on": "2022-07-01T09:00:00.000Z"
    }
  },
  {
    "model": "commons.skill",
    "fields": {
      "name": "UX Design",
      "skill_type": "T",
      "created_on": "2022-07-01T09:00:00.000Z"
    }
  },
  {
    "model": "commons.skill",
    "fields": {
      "name": "Unit Testing",
      "skill_type": "T",
      "created_on": "2022-07-01T09:00:00.000Z"
    }
  },
  {
    "model": "commons.skill",
    "fields": {
      "name": "Vue.js",
      "skill_type": "T",
      "created_on": "2022-07-01T09:00:00.000Z"
    }
  },
  {
    "model": "commons.skill",
    "fields": {
      "name": "WCF",
      "skill_type": "T",
      "created_on": "2022-07-01T09:00:00.000Z"
    }
  },
  {
    "model": "commons.skill",
    "fields": {
      "name": "WPF",
      "skill_type": "T",
      "created_on": "2022-07-01T09:00:00.000Z"
    }
  },
  {
    "model": "commons.skill",
    "fields": {
      "name": "Web Security",
      "skill_type": "T",
      "created_on": "2022-07-01T09:00:00.000Z"
    }
  },
  {
    "model": "commons.skill",
    "fields": {
      "name": "WebSockets",
      "skill_type": "T",
      "created_on": "2022-07-01T09:00:00.000Z"
    }
  },
  {
    "model": "commons.skill",
    "fields": {
      "name": "Xamarin",
      "skill_type": "T",
      "created_on": "2022-07-01T09:00:00.000Z"
    }
  },
  {
    "model": "commons.skill",
    "fields": {
      "name": "iOS",
      "skill_type": "T",
      "created_on": "2022-07-01T09:00:00.000Z"
    }
  },
  {
    "model": "commons.skill",
    "fields": {
      "name": "jQuery",
      "skill_type": "T",
      "created_on": "2022-07-01T09:00:00.000Z"
    }
  },
  {
    "model": "commons.skill",
    "fields": {
      "name": "API Design",
      "skill_type": "T",
      "created_on": "2022-07-01T09:00:00.000Z"
    }
  },
  {
    "model": "commons.skill",
    "fields": {
      "name": "Availability & Reliability",
      "skill_type": "T",
      "created_on": "2022-07-01T09:00:00.000Z"
    }
  },
  {
    "model": "commons.skill",
    "fields": {
      "name": "CAP Theorem",
      "skill_type": "T",
      "created_on": "2022-07-01T09:00:00.000Z"
    }
  },
  {
    "model": "commons.skill",
    "fields": {
      "name": "CDN",
      "skill_type": "T",
      "created_on": "2022-07-01T09:00:00.000Z"
    }
  },
  {
    "model": "commons.skill",
    "fields": {
      "name": "Caching",
      "skill_type": "T",
      "created_on": "2022-07-01T09:00:00.000Z"
    }
  },
  {
    "model": "commons.skill",
    "fields": {
      "name": "Concurrency",
      "skill_type": "T",
      "created_on": "2022-07-01T09:00:00.000Z"
    }
  },
  {
    "model": "commons.skill",
    "fields": {
      "name": "Cryptography",
      "skill_type": "T",
      "created_on": "2022-07-01T09:00:00.000Z"
    }
  },
  {
    "model": "commons.skill",
    "fields": {
      "name": "DDD",
      "skill_type": "T",
      "created_on": "2022-07-01T09:00:00.000Z"
    }
  },
  {
    "model": "commons.skill",
    "fields": {
      "name": "Databases",
      "skill_type": "T",
      "created_on": "2022-07-01T09:00:00.000Z"
    }
  },
  {
    "model": "commons.skill",
    "fields": {
      "name": "Docker",
      "skill_type": "T",
      "created_on": "2022-07-01T09:00:00.000Z"
    }
  },
  {
    "model": "commons.skill",
    "fields": {
      "name": "Kubernetes",
      "skill_type": "T",
      "created_on": "2022-07-01T09:00:00.000Z"
    }
  },
  {
    "model": "commons.skill",
    "fields": {
      "name": "Layering & Middleware",
      "skill_type": "T",
      "created_on": "2022-07-01T09:00:00.000Z"
    }
  },
  {
    "model": "commons.skill",
    "fields": {
      "name": "Load Balancing",
      "skill_type": "T",
      "created_on": "2022-07-01T09:00:00.000Z"
    }
  },
  {
    "model": "commons.skill",
    "fields": {
      "name": "Microservices",
      "skill_type": "T",
      "created_on": "2022-07-01T09:00:00.000Z"
    }
  },
  {
    "model": "commons.skill",
    "fields": {
      "name": "NoSQL",
      "skill_type": "T",
      "created_on": "2022-07-01T09:00:00.000Z"
    }
  },
  {
    "model": "commons.skill",
    "fields": {
      "name": "Reactive Systems",
      "skill_type": "T",
      "created_on": "2022-07-01T09:00:00.000Z"
    }
  },
  {
    "model": "commons.skill",
    "fields": {
      "name": "SOA",
      "skill_type": "T",
      "created_on": "2022-07-01T09:00:00.000Z"
    }
  },
  {
    "model": "commons.skill",
    "fields": {
      "name": "Software Architecture",
      "skill_type": "T",
      "created_on": "2022-07-01T09:00:00.000Z"
    }
  },
  {
    "model": "commons.skill",
    "fields": {
      "name": "Software Testing",
      "skill_type": "T",
      "created_on": "2022-07-01T09:00:00.000Z"
    }
  },
  {
    "model": "commons.skill",
    "fields": {
      "name": "HTML",
      "skill_type": "T",
      "created_on": "2022-07-01T09:00:00.000Z"
    }
  },
  {
    "model": "commons.skill",
    "fields": {
      "name": "Bash/Shell",
      "skill_type": "T",
      "created_on": "2022-07-01T09:00:00.000Z"
    }
  },
  {
    "model": "commons.skill",
    "fields": {
      "name": "C++",
      "skill_type": "T",
      "created_on": "2022-07-01T09:00:00.000Z"
    }
  },
  {
    "model": "commons.skill",
    "fields": {
      "name": "C",
      "skill_type": "T",
      "created_on": "2022-07-01T09:00:00.000Z"
    }
  },
  {
    "model": "commons.skill",
    "fields": {
      "name": "PowerShell",
      "skill_type": "T",
      "created_on": "2022-07-01T09:00:00.000Z"
    }
  },
  {
    "model": "commons.skill",
    "fields": {
      "name": "Go",
      "skill_type": "T",
      "created_on": "2022-07-01T09:00:00.000Z"
    }
  },
  {
    "model": "commons.skill",
    "fields": {
      "name": "Rust",
      "skill_type": "T",
      "created_on": "2022-07-01T09:00:00.000Z"
    }
  },
  {
    "model": "commons.skill",
    "fields": {
      "name": "Dart",
      "skill_type": "T",
      "created_on": "2022-07-01T09:00:00.000Z"
    }
  },
  {
    "model": "commons.skill",
    "fields": {
      "name": "Assembly",
      "skill_type": "T",
      "created_on": "2022-07-01T09:00:00.000Z"
    }
  },
  {
    "model": "commons.skill",
    "fields": {
      "name": "Swift",
      "skill_type": "T",
      "created_on": "2022-07-01T09:00:00.000Z"
    }
  },
  {
    "model": "commons.skill",
    "fields": {
      "name": "R",
      "skill_type": "T",
      "created_on": "2022-07-01T09:00:00.000Z"
    }
  },
  {
    "model": "commons.skill",
    "fields": {
      "name": "VBA",
      "skill_type": "T",
      "created_on": "2022-07-01T09:00:00.000Z"
    }
  },
  {
    "model": "commons.skill",
    "fields": {
      "name": "MATLAB",
      "skill_type": "T",
      "created_on": "2022-07-01T09:00:00.000Z"
    }
  },
  {
    "model": "commons.skill",
    "fields": {
      "name": "Lua",
      "skill_type": "T",
      "created_on": "2022-07-01T09:00:00.000Z"
    }
  },
  {
    "model": "commons.skill",
    "fields": {
      "name": "Groovy",
      "skill_type": "T",
      "created_on": "2022-07-01T09:00:00.000Z"
    }
  },
  {
    "model": "commons.skill",
    "fields": {
      "name": "Delphi",
      "skill_type": "T",
      "created_on": "2022-07-01T09:00:00.000Z"
    }
  },
  {
    "model": "commons.skill",
    "fields": {
      "name": "Scala",
      "skill_type": "T",
      "created_on": "2022-07-01T09:00:00.000Z"
    }
  },
  {
    "model": "commons.skill",
    "fields": {
      "name": "Perl",
      "skill_type": "T",
      "created_on": "2022-07-01T09:00:00.000Z"
    }
  },
  {
    "model": "commons.skill",
    "fields": {
      "name": "Haskell",
      "skill_type": "T",
      "created_on": "2022-07-01T09:00:00.000Z"
    }
  },
  {
    "model": "commons.skill",
    "fields": {
      "name": "Elixir",
      "skill_type": "T",
      "created_on": "2022-07-01T09:00:00.000Z"
    }
  },
  {
    "model": "commons.skill",
    "fields": {
      "name": "Julia",
      "skill_type": "T",
      "created_on": "2022-07-01T09:00:00.000Z"
    }
  },
  {
    "model": "commons.skill",
    "fields": {
      "name": "Clojure",
      "skill_type": "T",
      "created_on": "2022-07-01T09:00:00.000Z"
    }
  },
  {
    "model": "commons.skill",
    "fields": {
      "name": "Solidity",
      "skill_type": "T",
      "created_on": "2022-07-01T09:00:00.000Z"
    }
  },
  {
    "model": "commons.skill",
    "fields": {
      "name": "LISP",
      "skill_type": "T",
      "created_on": "2022-07-01T09:00:00.000Z"
    }
  },
  {
    "model": "commons.skill",
    "fields": {
      "name": "F#",
      "skill_type": "T",
      "created_on": "2022-07-01T09:00:00.000Z"
    }
  },
  {
    "model": "commons.skill",
    "fields": {
      "name": "Fortran",
      "skill_type": "T",
      "created_on": "2022-07-01T09:00:00.000Z"
    }
  },
  {
    "model": "commons.skill",
    "fields": {
      "name": "Erlang",
      "skill_type": "T",
      "created_on": "2022-07-01T09:00:00.000Z"
    }
  },
  {
    "model": "commons.skill",
    "fields": {
      "name": "APL",
      "skill_type": "T",
      "created_on": "2022-07-01T09:00:00.000Z"
    }
  },
  {
    "model": "commons.skill",
    "fields": {
      "name": "COBOL",
      "skill_type": "T",
      "created_on": "2022-07-01T09:00:00.000Z"
    }
  },
  {
    "model": "commons.skill",
    "fields": {
      "name": "SAS",
      "skill_type": "T",
      "created_on": "2022-07-01T09:00:00.000Z"
    }
  },
  {
    "model": "commons.skill",
    "fields": {
      "name": "OCaml",
      "skill_type": "T",
      "created_on": "2022-07-01T09:00:00.000Z"
    }
  },
  {
    "model": "commons.skill",
    "fields": {
      "name": "Crystal",
      "skill_type": "T",
      "created_on": "2022-07-01T09:00:00.000Z"
    }
  },
  {
    "model": "commons.skill",
    "fields": {
      "name": "PostgreSQL",
      "skill_type": "T",
      "created_on": "2022-07-01T09:00:00.000Z"
    }
  },
  {
    "model": "commons.skill",
    "fields": {
      "name": "SQLite",
      "skill_type": "T",
      "created_on": "2022-07-01T09:00:00.000Z"
    }
  },
  {
    "model": "commons.skill",
    "fields": {
      "name": "Microsoft SQL Server",
      "skill_type": "T",
      "created_on": "2022-07-01T09:00:00.000Z"
    }
  },
  {
    "model": "commons.skill",
    "fields": {
      "name": "MariaDB",
      "skill_type": "T",
      "created_on": "2022-07-01T09:00:00.000Z"
    }
  },
  {
    "model": "commons.skill",
    "fields": {
      "name": "Elasticsearch",
      "skill_type": "T",
      "created_on": "2022-07-01T09:00:00.000Z"
    }
  },
  {
    "model": "commons.skill",
    "fields": {
      "name": "Oracle",
      "skill_type": "T",
      "created_on": "2022-07-01T09:00:00.000Z"
    }
  },
  {
    "model": "commons.skill",
    "fields": {
      "name": "Firebase Realtime Database",
      "skill_type": "T",
      "created_on": "2022-07-01T09:00:00.000Z"
    }
  },
  {
    "model": "commons.skill",
    "fields": {
      "name": "DynamoDB",
      "skill_type": "T",
      "created_on": "2022-07-01T09:00:00.000Z"
    }
  },
  {
    "model": "commons.skill",
    "fields": {
      "name": "Cloud Firestore",
      "skill_type": "T",
      "created_on": "2022-07-01T09:00:00.000Z"
    }
  },
  {
    "model": "commons.skill",
    "fields": {
      "name": "Cassandra",
      "skill_type": "T",
      "created_on": "2022-07-01T09:00:00.000Z"
    }
  },
  {
    "model": "commons.skill",
    "fields": {
      "name": "Neo4j",
      "skill_type": "T",
      "created_on": "2022-07-01T09:00:00.000Z"
    }
  },
  {
    "model": "commons.skill",
    "fields": {
      "name": "IBM DB2",
      "skill_type": "T",
      "created_on": "2022-07-01T09:00:00.000Z"
    }
  },
  {
    "model": "commons.skill",
    "fields": {
      "name": "Couchbase",
      "skill_type": "T",
      "created_on": "2022-07-01T09:00:00.000Z"
    }
  },
  {
    "model": "commons.skill",
    "fields": {
      "name": "CouchDB",
      "skill_type": "T",
      "created_on": "2022-07-01T09:00:00.000Z"
    }
  },
  {
    "model": "commons.skill",
    "fields": {
      "name": "AWS",
      "skill_type": "T",
      "created_on": "2022-07-01T09:00:00.000Z"
    }
  },
  {
    "model": "commons.skill",
    "fields": {
      "name": "Microsoft Azure",
      "skill_type": "T",
      "created_on": "2022-07-01T09:00:00.000Z"
    }
  },
  {
    "model": "commons.skill",
    "fields": {
      "name": "Google Cloud",
      "skill_type": "T",
      "created_on": "2022-07-01T09:00:00.000Z"
    }
  },
  {
    "model": "commons.skill",
    "fields": {
      "name": "Firebase",
      "skill_type": "T",
      "created_on": "2022-07-01T09:00:00.000Z"
    }
  },
  {
    "model": "commons.skill",
    "fields": {
      "name": "Heroku",
      "skill_type": "T",
      "created_on": "2022-07-01T09:00:00.000Z"
    }
  },
  {
    "model": "commons.skill",
    "fields": {
      "name": "DigitalOcean",
      "skill_type": "T",
      "created_on": "2022-07-01T09:00:00.000Z"
    }
  },
  {
    "model": "commons.skill",
    "fields": {
      "name": "VMware",
      "skill_type": "T",
      "created_on": "2022-07-01T09:00:00.000Z"
    }
  },
  {
    "model": "commons.skill",
    "fields": {
      "name": "Managed Hosting",
      "skill_type": "T",
      "created_on": "2022-07-01T09:00:00.000Z"
    }
  },
  {
    "model": "commons.skill",
    "fields": {
      "name": "Linode",
      "skill_type": "T",
      "created_on": "2022-07-01T09:00:00.000Z"
    }
  },
  {
    "model": "commons.skill",
    "fields": {
      "name": "OVH",
      "skill_type": "T",
      "created_on": "2022-07-01T09:00:00.000Z"
    }
  },
  {
    "model": "commons.skill",
    "fields": {
      "name": "Oracle Cloud Infrastructure",
      "skill_type": "T",
      "created_on": "2022-07-01T09:00:00.000Z"
    }
  },
  {
    "model": "commons.skill",
    "fields": {
      "name": "OpenStack",
      "skill_type": "T",
      "created_on": "2022-07-01T09:00:00.000Z"
    }
  },
  {
    "model": "commons.skill",
    "fields": {
      "name": "IBM Cloud",
      "skill_type": "T",
      "created_on": "2022-07-01T09:00:00.000Z"
    }
  },
  {
    "model": "commons.skill",
    "fields": {
      "name": "IBM Watson",
      "skill_type": "T",
      "created_on": "2022-07-01T09:00:00.000Z"
    }
  },
  {
    "model": "commons.skill",
    "fields": {
      "name": "Colocation",
      "skill_type": "T",
      "created_on": "2022-07-01T09:00:00.000Z"
    }
  },
  {
    "model": "commons.skill",
    "fields": {
      "name": "React.js",
      "skill_type": "T",
      "created_on": "2022-07-01T09:00:00.000Z"
    }
  },
  {
    "model": "commons.skill",
    "fields": {
      "name": "Express",
      "skill_type": "T",
      "created_on": "2022-07-01T09:00:00.000Z"
    }
  },
  {
    "model": "commons.skill",
    "fields": {
      "name": "ASP.NET Core",
      "skill_type": "T",
      "created_on": "2022-07-01T09:00:00.000Z"
    }
  },
  {
    "model": "commons.skill",
    "fields": {
      "name": "Django",
      "skill_type": "T",
      "created_on": "2022-07-01T09:00:00.000Z"
    }
  },
  {
    "model": "commons.skill",
    "fields": {
      "name": "Flask",
      "skill_type": "T",
      "created_on": "2022-07-01T09:00:00.000Z"
    }
  },
  {
    "model": "commons.skill",
    "fields": {
      "name": "Next.js",
      "skill_type": "T",
      "created_on": "2022-07-01T09:00:00.000Z"
    }
  },
  {
    "model": "commons.skill",
    "fields": {
      "name": "Angular.js",
      "skill_type": "T",
      "created_on": "2022-07-01T09:00:00.000Z"
    }
  },
  {
    "model": "commons.skill",
    "fields": {
      "name": "FastAPI",
      "skill_type": "T",
      "created_on": "2022-07-01T09:00:00.000Z"
    }
  },
  {
    "model": "commons.skill",
    "fields": {
      "name": "Svelte",
      "skill_type": "T",
      "created_on": "2022-07-01T09:00:00.000Z"
    }
  },
  {
    "model": "commons.skill",
    "fields": {
      "name": "Blazor",
      "skill_type": "T",
      "created_on": "2022-07-01T09:00:00.000Z"
    }
  },
  {
    "model": "commons.skill",
    "fields": {
      "name": "Nuxt.js",
      "skill_type": "T",
      "created_on": "2022-07-01T09:00:00.000Z"
    }
  },
  {
    "model": "commons.skill",
    "fields": {
      "name": "Symfony",
      "skill_type": "T",
      "created_on": "2022-07-01T09:00:00.000Z"
    }
  },
  {
    "model": "commons.skill",
    "fields": {
      "name": "Gatsby",
      "skill_type": "T",
      "created_on": "2022-07-01T09:00:00.000Z"
    }
  },
  {
    "model": "commons.skill",
    "fields": {
      "name": "Drupal",
      "skill_type": "T",
      "created_on": "2022-07-01T09:00:00.000Z"
    }
  },
  {
    "model": "commons.skill",
    "fields": {
      "name": "Phoenix",
      "skill_type": "T",
      "created_on": "2022-07-01T09:00:00.000Z"
    }
  },
  {
    "model": "commons.skill",
    "fields": {
      "name": "Fastify",
      "skill_type": "T",
      "created_on": "2022-07-01T09:00:00.000Z"
    }
  },
  {
    "model": "commons.skill",
    "fields": {
      "name": "Deno",
      "skill_type": "T",
      "created_on": "2022-07-01T09:00:00.000Z"
    }
  },
  {
    "model": "commons.skill",
    "fields": {
      "name": "Play Framework",
      "skill_type": "T",
      "created_on": "2022-07-01T09:00:00.000Z"
    }
  },
  {
    "model": "commons.skill",
    "fields": {
      "name": ".NET",
      "skill_type": "T",
      "created_on": "2022-07-01T09:00:00.000Z"
    }
  },
  {
    "model": "commons.skill",
    "fields": {
      "name": "NumPy",
      "skill_type": "T",
      "created_on": "2022-07-01T09:00:00.000Z"
    }
  },
  {
    "model": "commons.skill",
    "fields": {
      "name": "Pandas",
      "skill_type": "T",
      "created_on": "2022-07-01T09:00:00.000Z"
    }
  },
  {
    "model": "commons.skill",
    "fields": {
      "name": "TensorFlow",
      "skill_type": "T",
      "created_on": "2022-07-01T09:00:00.000Z"
    }
  },
  {
    "model": "commons.skill",
    "fields": {
      "name": "Scikit-learn",
      "skill_type": "T",
      "created_on": "2022-07-01T09:00:00.000Z"
    }
  },
  {
    "model": "commons.skill",
    "fields": {
      "name": "Apache Kafka",
      "skill_type": "T",
      "created_on": "2022-07-01T09:00:00.000Z"
    }
  },
  {
    "model": "commons.skill",
    "fields": {
      "name": "Electron",
      "skill_type": "T",
      "created_on": "2022-07-01T09:00:00.000Z"
    }
  },
  {
    "model": "commons.skill",
    "fields": {
      "name": "Torch/PyTorch",
      "skill_type": "T",
      "created_on": "2022-07-01T09:00:00.000Z"
    }
  },
  {
    "model": "commons.skill",
    "fields": {
      "name": "Qt",
      "skill_type": "T",
      "created_on": "2022-07-01T09:00:00.000Z"
    }
  },
  {
    "model": "commons.skill",
    "fields": {
      "name": "Keras",
      "skill_type": "T",
      "created_on": "2022-07-01T09:00:00.000Z"
    }
  },
  {
    "model": "commons.skill",
    "fields": {
      "name": "Apache Spark",
      "skill_type": "T",
      "created_on": "2022-07-01T09:00:00.000Z"
    }
  },
  {
    "model": "commons.skill",
    "fields": {
      "name": "Cordova",
      "skill_type": "T",
      "created_on": "2022-07-01T09:00:00.000Z"
    }
  },
  {
    "model": "commons.skill",
    "fields": {
      "name": "Hadoop",
      "skill_type": "T",
      "created_on": "2022-07-01T09:00:00.000Z"
    }
  },
  {
    "model": "commons.skill",
    "fields": {
      "name": "GTK",
      "skill_type": "T",
      "created_on": "2022-07-01T09:00:00.000Z"
    }
  },
  {
    "model": "commons.skill",
    "fields": {
      "name": "Capacitor",
      "skill_type": "T",
      "created_on": "2022-07-01T09:00:00.000Z"
    }
  },
  {
    "model": "commons.skill",
    "fields": {
      "name": "Tidyverse",
      "skill_type": "T",
      "created_on": "2022-07-01T09:00:00.000Z"
    }
  },
  {
    "model": "commons.skill",
    "fields": {
      "name": "Hugging Face Transformers",
      "skill_type": "T",
      "created_on": "2022-07-01T09:00:00.000Z"
    }
  },
  {
    "model": "commons.skill",
    "fields": {
      "name": "Uno Platform",
      "skill_type": "T",
      "created_on": "2022-07-01T09:00:00.000Z"
    }
  },
  {
    "model": "commons.skill",
    "fields": {
      "name": "npm",
      "skill_type": "T",
      "created_on": "2022-07-01T09:00:00.000Z"
    }
  },
  {
    "model": "commons.skill",
    "fields": {
      "name": "Yarn",
      "skill_type": "T",
      "created_on": "2022-07-01T09:00:00.000Z"
    }
  },
  {
    "model": "commons.skill",
    "fields": {
      "name": "Homebrew",
      "skill_type": "T",
      "created_on": "2022-07-01T09:00:00.000Z"
    }
  },
  {
    "model": "commons.skill",
    "fields": {
      "name": "Terraform",
      "skill_type": "T",
      "created_on": "2022-07-01T09:00:00.000Z"
    }
  },
  {
    "model": "commons.skill",
    "fields": {
      "name": "Unity 3D",
      "skill_type": "T",
      "created_on": "2022-07-01T09:00:00.000Z"
    }
  },
  {
    "model": "commons.skill",
    "fields": {
      "name": "Ansible",
      "skill_type": "T",
      "created_on": "2022-07-01T09:00:00.000Z"
    }
  },
  {
    "model": "commons.skill",
    "fields": {
      "name": "Unreal Engine",
      "skill_type": "T",
      "created_on": "2022-07-01T09:00:00.000Z"
    }
  },
  {
    "model": "commons.skill",
    "fields": {
      "name": "Puppet",
      "skill_type": "T",
      "created_on": "2022-07-01T09:00:00.000Z"
    }
  },
  {
    "model": "commons.skill",
    "fields": {
      "name": "Chef",
      "skill_type": "T",
      "created_on": "2022-07-01T09:00:00.000Z"
    }
  },
  {
    "model": "commons.skill",
    "fields": {
      "name": "Pulumi",
      "skill_type": "T",
      "created_on": "2022-07-01T09:00:00.000Z"
    }
  },
  {
    "model": "commons.skill",
    "fields": {
      "name": "Flow",
      "skill_type": "T",
      "created_on": "2022-07-01T09:00:00.000Z"
    }
  },
  {
    "model": "commons.skill",
    "fields": {
      "name": "Visual Studio Code",
      "skill_type": "T",
      "created_on": "2022-07-01T09:00:00.000Z"
    }
  },
  {
    "model": "commons.skill",
    "fields": {
      "name": "Visual Studio",
      "skill_type": "T",
      "created_on": "2022-07-01T09:00:00.000Z"
    }
  },
  {
    "model": "commons.skill",
    "fields": {
      "name": "IntelliJ",
      "skill_type": "T",
      "created_on": "2022-07-01T09:00:00.000Z"
    }
  },
  {
    "model": "commons.skill",
    "fields": {
      "name": "Notepad++",
      "skill_type": "T",
      "created_on": "2022-07-01T09:00:00.000Z"
    }
  },
  {
    "model": "commons.skill",
    "fields": {
      "name": "Vim",
      "skill_type": "T",
      "created_on": "2022-07-01T09:00:00.000Z"
    }
  },
  {
    "model": "commons.skill",
    "fields": {
      "name": "Android Studio",
      "skill_type": "T",
      "created_on": "2022-07-01T09:00:00.000Z"
    }
  },
  {
    "model": "commons.skill",
    "fields": {
      "name": "PyCharm",
      "skill_type": "T",
      "created_on": "2022-07-01T09:00:00.000Z"
    }
  },
  {
    "model": "commons.skill",
    "fields": {
      "name": "Sublime Text",
      "skill_type": "T",
      "created_on": "2022-07-01T09:00:00.000Z"
    }
  },
  {
    "model": "commons.skill",
    "fields": {
      "name": "Eclipse",
      "skill_type": "T",
      "created_on": "2022-07-01T09:00:00.000Z"
    }
  },
  {
    "model": "commons.skill",
    "fields": {
      "name": "IPython/Jupyter",
      "skill_type": "T",
      "created_on": "2022-07-01T09:00:00.000Z"
    }
  },
  {
    "model": "commons.skill",
    "fields": {
      "name": "Xcode",
      "skill_type": "T",
      "created_on": "2022-07-01T09:00:00.000Z"
    }
  },
  {
    "model": "commons.skill",
    "fields": {
      "name": "Atom",
      "skill_type": "T",
      "created_on": "2022-07-01T09:00:00.000Z"
    }
  },
  {
    "model": "commons.skill",
    "fields": {
      "name": "Nano",
      "skill_type": "T",
      "created_on": "2022-07-01T09:00:00.000Z"
    }
  },
  {
    "model": "commons.skill",
    "fields": {
      "name": "Webstorm",
      "skill_type": "T",
      "created_on": "2022-07-01T09:00:00.000Z"
    }
  },
  {
    "model": "commons.skill",
    "fields": {
      "name": "PhpStorm",
      "skill_type": "T",
      "created_on": "2022-07-01T09:00:00.000Z"
    }
  },
  {
    "model": "commons.skill",
    "fields": {
      "name": "Neovim",
      "skill_type": "T",
      "created_on": "2022-07-01T09:00:00.000Z"
    }
  },
  {
    "model": "commons.skill",
    "fields": {
      "name": "NetBeans",
      "skill_type": "T",
      "created_on": "2022-07-01T09:00:00.000Z"
    }
  },
  {
    "model": "commons.skill",
    "fields": {
      "name": "CLion",
      "skill_type": "T",
      "created_on": "2022-07-01T09:00:00.000Z"
    }
  },
  {
    "model": "commons.skill",
    "fields": {
      "name": "Rider",
      "skill_type": "T",
      "created_on": "2022-07-01T09:00:00.000Z"
    }
  },
  {
    "model": "commons.skill",
    "fields": {
      "name": "Emacs",
      "skill_type": "T",
      "created_on": "2022-07-01T09:00:00.000Z"
    }
  },
  {
    "model": "commons.skill",
    "fields": {
      "name": "RStudio",
      "skill_type": "T",
      "created_on": "2022-07-01T09:00:00.000Z"
    }
  },
  {
    "model": "commons.skill",
    "fields": {
      "name": "GoLand",
      "skill_type": "T",
      "created_on": "2022-07-01T09:00:00.000Z"
    }
  },
  {
    "model": "commons.skill",
    "fields": {
      "name": "RAD Studio (Delphi, C++ Builder)",
      "skill_type": "T",
      "created_on": "2022-07-01T09:00:00.000Z"
    }
  },
  {
    "model": "commons.skill",
    "fields": {
      "name": "Qt Creator",
      "skill_type": "T",
      "created_on": "2022-07-01T09:00:00.000Z"
    }
  },
  {
    "model": "commons.skill",
    "fields": {
      "name": "Spyder",
      "skill_type": "T",
      "created_on": "2022-07-01T09:00:00.000Z"
    }
  },
  {
    "model": "commons.skill",
    "fields": {
      "name": "RubyMine",
      "skill_type": "T",
      "created_on": "2022-07-01T09:00:00.000Z"
    }
  },
  {
    "model": "commons.skill",
    "fields": {
      "name": "TextMate",
      "skill_type": "T",
      "created_on": "2022-07-01T09:00:00.000Z"
    }
  },
  {
    "model": "commons.skill",
    "fields": {
      "name": "Jira Work Management",
      "skill_type": "T",
      "created_on": "2022-07-01T09:00:00.000Z"
    }
  },
  {
    "model": "commons.skill",
    "fields": {
      "name": "Confluence",
      "skill_type": "T",
      "created_on": "2022-07-01T09:00:00.000Z"
    }
  },
  {
    "model": "commons.skill",
    "fields": {
      "name": "Trello",
      "skill_type": "T",
      "created_on": "2022-07-01T09:00:00.000Z"
    }
  },
  {
    "model": "commons.skill",
    "fields": {
      "name": "Notion",
      "skill_type": "T",
      "created_on": "2022-07-01T09:00:00.000Z"
    }
  },
  {
    "model": "commons.skill",
    "fields": {
      "name": "Asana",
      "skill_type": "T",
      "created_on": "2022-07-01T09:00:00.000Z"
    }
  },
  {
    "model": "commons.skill",
    "fields": {
      "name": "ClickUp",
      "skill_type": "T",
      "created_on": "2022-07-01T09:00:00.000Z"
    }
  },
  {
    "model": "commons.skill",
    "fields": {
      "name": "Microsoft Planner",
      "skill_type": "T",
      "created_on": "2022-07-01T09:00:00.000Z"
    }
  },
  {
    "model": "commons.skill",
    "fields": {
      "name": "Stack Overflow for Teams",
      "skill_type": "T",
      "created_on": "2022-07-01T09:00:00.000Z"
    }
  },
  {
    "model": "commons.skill",
    "fields": {
      "name": "monday.com",
      "skill_type": "T",
      "created_on": "2022-07-01T09:00:00.000Z"
    }
  },
  {
    "model": "commons.skill",
    "fields": {
      "name": "Airtable",
      "skill_type": "T",
      "created_on": "2022-07-01T09:00:00.000Z"
    }
  },
  {
    "model": "commons.skill",
    "fields": {
      "name": "Microsoft Lists",
      "skill_type": "T",
      "created_on": "2022-07-01T09:00:00.000Z"
    }
  },
  {
    "model": "commons.skill",
    "fields": {
      "name": "Smartsheet",
      "skill_type": "T",
      "created_on": "2022-07-01T09:00:00.000Z"
    }
  },
  {
    "model": "commons.skill",
    "fields": {
      "name": "Wrike",
      "skill_type": "T",
      "created_on": "2022-07-01T09:00:00.000Z"
    }
  },
  {
    "model": "commons.skill",
    "fields": {
      "name": "Adobe Workfront",
      "skill_type": "T",
      "created_on": "2022-07-01T09:00:00.000Z"
    }
  },
  {
    "model": "commons.skill",
    "fields": {
      "name": "DingTalk (Teambition)",
      "skill_type": "T",
      "created_on": "2022-07-01T09:00:00.000Z"
    }
  },
  {
    "model": "commons.skill",
    "fields": {
      "name": "Swit",
      "skill_type": "T",
      "created_on": "2022-07-01T09:00:00.000Z"
    }
  },
  {
    "model": "commons.skill",
    "fields": {
      "name": "Workzone",
      "skill_type": "T",
      "created_on": "2022-07-01T09:00:00.000Z"
    }
  },
  {
    "model": "commons.skill",
    "fields": {
      "name": "Planview Projectplace or Clarizen",
      "skill_type": "T",
      "created_on": "2022-07-01T09:00:00.000Z"
    }
  },
  {
    "model": "commons.skill",
    "fields": {
      "name": "Cerri",
      "skill_type": "T",
      "created_on": "2022-07-01T09:00:00.000Z"
    }
  },
  {
    "model": "commons.skill",
    "fields": {
      "name": "Wimi",
      "skill_type": "T",
      "created_on": "2022-07-01T09:00:00.000Z"
    }
  },
  {
    "model": "commons.skill",
    "fields": {
      "name": "Leankor",
      "skill_type": "T",
      "created_on": "2022-07-01T09:00:00.000Z"
    }
  },
  {
    "model": "commons.skill",
    "fields": {
      "name": "Zoom",
      "skill_type": "T",
      "created_on": "2022-07-01T09:00:00.000Z"
    }
  },
  {
    "model": "commons.skill",
    "fields": {
      "name": "Microsoft Teams",
      "skill_type": "T",
      "created_on": "2022-07-01T09:00:00.000Z"
    }
  },
  {
    "model": "commons.skill",
    "fields": {
      "name": "Slack",
      "skill_type": "T",
      "created_on": "2022-07-01T09:00:00.000Z"
    }
  },
  {
    "model": "commons.skill",
    "fields": {
      "name": "Google Chat",
      "skill_type": "T",
      "created_on": "2022-07-01T09:00:00.000Z"
    }
  },
  {
    "model": "commons.skill",
    "fields": {
      "name": "Cisco Webex Teams",
      "skill_type": "T",
      "created_on": "2022-07-01T09:00:00.000Z"
    }
  },
  {
    "model": "commons.skill",
    "fields": {
      "name": "Mattermost",
      "skill_type": "T",
      "created_on": "2022-07-01T09:00:00.000Z"
    }
  },
  {
    "model": "commons.skill",
    "fields": {
      "name": "Rocketchat",
      "skill_type": "T",
      "created_on": "2022-07-01T09:00:00.000Z"
    }
  },
  {
    "model": "commons.skill",
    "fields": {
      "name": "RingCentral",
      "skill_type": "T",
      "created_on": "2022-07-01T09:00:00.000Z"
    }
  },
  {
    "model": "commons.skill",
    "fields": {
      "name": "Symphony",
      "skill_type": "T",
      "created_on": "2022-07-01T09:00:00.000Z"
    }
  },
  {
    "model": "commons.skill",
    "fields": {
      "name": "Wire",
      "skill_type": "T",
      "created_on": "2022-07-01T09:00:00.000Z"
    }
  },
  {
    "model": "commons.skill",
    "fields": {
      "name": "Wickr",
      "skill_type": "T",
      "created_on": "2022-07-01T09:00:00.000Z"
    }
  },
  {
    "model": "commons.skill",
    "fields": {
      "name": "Unify Circuit",
      "skill_type": "T",
      "created_on": "2022-07-01T09:00:00.000Z"
    }
  },
  {
    "model": "commons.skill",
    "fields": {
      "name": "Coolfire Core",
      "skill_type": "T",
      "created_on": "2022-07-01T09:00:00.000Z"
    }
  },
  {
    "model": "commons.skill",
    "fields": {
      "name": "IBM Cloud or Watson",
      "skill_type": "T",
      "created_on": "2022-07-01T09:00:00.000Z"
    }
  },
  {
    "model": "commons.skill",
    "fields": {
      "name": "HTML/CSS",
      "skill_type": "T",
      "created_on": "2022-07-01T09:00:00.000Z"
    }
  },
  {
    "model": "commons.skill",
    "fields": {
      "name": "SVN",
      "skill_type": "T",
      "created_on": "2022-07-01T09:00:00.000Z"
    }
  },
  {
    "model": "commons.skill",
    "fields": {
      "name": "Mercurial",
      "skill_type": "T",
      "created_on": "2022-07-01T09:00:00.000Z"
    }
  },
  {
    "model": "commons.skill",
    "fields": {
      "name": "GitHub",
      "skill_type": "T",
      "created_on": "2022-07-01T09:00:00.000Z"
    }
  },
  {
    "model": "commons.skill",
    "fields": {
      "name": "GitLab",
      "skill_type": "T",
      "created_on": "2022-07-01T09:00:00.000Z"
    }
  },
  {
    "model": "commons.skill",
    "fields": {
      "name": "Bitbucket",
      "skill_type": "T",
      "created_on": "2022-07-01T09:00:00.000Z"
    }
  },
  {
    "model": "commons.skill",
    "fields": {
      "name": "Azure Repos",
      "skill_type": "T",
      "created_on": "2022-07-01T09:00:00.000Z"
    }
  },
  {
    "model": "commons.skill",
    "fields": {
      "name": "AWS CodeCommit",
      "skill_type": "T",
      "created_on": "2022-07-01T09:00:00.000Z"
    }
  },
  {
    "model": "commons.skill",
    "fields": {
      "name": "Communication",
      "skill_type": "NT",
      "created_on": "2022-07-01T09:00:00.000Z"
    }
  },
  {
    "model": "commons.skill",
    "fields": {
      "name": "Leadership",
      "skill_type": "NT",
      "created_on": "2022-07-01T09:00:00.000Z"
    }
  }
]